[
  {
    "title":"South Africa tour of India, 2022",
    "img":"https://i.ibb.co/TgwqwCp/Untitled-design-1-14-748x430.png",
    "description":"Match NO : 2nd T20I",
    "date":"02/10/2022",
    "srn":"feed"
  },
  {
    "title":"TOSS PREDICTION",
    "img":"https://i.ibb.co/TgwqwCp/Untitled-design-1-14-748x430.png",
    "description":"Our Experts Will Give 100% Sure Toss Winner",
    "date":"02/10/2022",
    "srn":"predict"
  },
  {
    "title":"IND vs RSA",
    "img":"https://i.ibb.co/TgwqwCp/Untitled-design-1-14-748x430.png",
    "description":"Toss Winner : SOUTH AFRICA ",
    "date":"https://t.me/ipltoss_king",
    "srn":"web"
  },
  {
    "title":"IND vs RSA",
    "img":"https://i.ibb.co/TgwqwCp/Untitled-design-1-14-748x430.png",
    "description":"MATCH Winner : India ",
    "date":"https://t.me/ipltoss_king",
    "srn":"xweb"
  }
]
