[
{
  "banimg1":"https://i.ibb.co/WpdbGyh/IPL-2022-Points-Table-Indian-Premier-League-2022-Team-Standings.jpg",
  "banlink1":"https://www.iplprediction.com/ipl-prediction-ipl-2021-points-table/",
  "bansrn1":"xweb",
  "bantitle1":"Test",
  "banimg2":"https://i.ibb.co/LnY4yfS/IPL-Quiz.jpg",
  "banlink2":"https://733.go.qureka.com/",
  "bansrn2":"xweb",
  "bantitle2":"Test",
  "banimg3":"https://i.ibb.co/fk05F1d/aus-vs-sl.jpg",
  "banlink3":"https://commondp.github.io/P2.0/path/ipl.json",
  "bansrn3":"cat",
  "bantitle3":"Test",
  "banimg1":"https://i.ibb.co/WpdbGyh/IPL-2022-Points-Table-Indian-Premier-League-2022-Team-Standings.jpg",
  "mainpath":"https://commondp.github.io/P2.0/Home/index.json",
  "telegram":"https://t.me/ipltoss_king",
  "banad":"https://www.unfe.org/wp-content/uploads/2019/04/SM-placeholder.png",
  "banlink":"https://google.com"
},
{
  "banimg1":"https://i.ibb.co/WpdbGyh/IPL-2022-Points-Table-Indian-Premier-League-2022-Team-Standings.jpg",
  "banlink1":"https://www.iplprediction.com/ipl-prediction-ipl-2021-points-table/",
  "bansrn1":"xweb",
  "bantitle1":"Test",
  "banimg2":"https://i.ibb.co/YkB8YZC/IPL-Schedule-2022-pdf.jpg",
  "banlink2":"https://www.iplprediction.com/tata-ipl-2022-schedule/",
  "bansrn2":"xweb",
  "bantitle2":"Test",
  "banimg3":"https://i.ibb.co/fk05F1d/aus-vs-sl.jpg",
  "banlink3":"https://commondp.github.io/P2.0/path/ipl.json",
  "bansrn3":"cat",
  "bantitle3":"Test",
  "mainpath":"https://commondp.github.io/P2.0/Home/index.json",
  "telegram":"https://t.me/ipltoss_king",
  "banad":"https://www.unfe.org/wp-content/uploads/2019/04/SM-placeholder.png",
  "banlink":"https://google.com"
}
]
